{
  "protocol_version" : "0.0.6",
  "configuration" : {
    "version" : "(6.13.0) (explicit/16ec7cb2)",
    "tlc" : "__thread",
    "sigsgev" : "normal",
    "notifications" : "kqueue",
    "architecture" : "arm64",
    "disabled_features" : "com,shared_perfcounters",
    "smallconfig" : "disabled",
    "bigarrays" : "disabled",
    "softdebug" : "enabled",
    "interpreter" : "enabled",
    "llvm_support" : "disabled",
    "suspend" : "preemptive"
  },
  "memory" : {
    "Resident Size" : "1780023296",
    "Virtual Size" : "423120355328",
    "minor_gc_time" : "0",
    "major_gc_time" : "172283",
    "minor_gc_count" : "0",
    "major_gc_count" : "4",
    "major_gc_time_concurrent" : "0"
 },
  "threads" : [
 {
    "is_managed" : false,
    "offset_free_hash" : "0x0",
    "offset_rich_hash" : "0x0",
    "crashed" : false,
    "native_thread_id" : "0x29ea07000",
    "thread_info_addr" : "0x1355bea00",
    "thread_name" : "Thread Pool I/O Selector",
    "ctx" : {
      "IP" : "0x18b47aff0",
      "SP" : "0x29ea06ae0",
      "BP" : "0x29ea06ce0"
  },
    "unmanaged_frames" : [
  {
      "is_managed" : "false",
      "native_address" : "0x29008119c",
      "native_offset" : "0x00000"
   }
,
  {
      "is_managed" : "false",
      "native_address" : "0x2901b8518",
      "native_offset" : "0x00000"
   }
,
  {
      "is_managed" : "false",
      "native_address" : "0x2901b8874",
      "native_offset" : "0x00000"
   }
,
  {
      "is_managed" : "false",
      "native_address" : "0x2901b863c",
      "native_offset" : "0x00000"
   }
,
  {
      "is_managed" : "false",
      "native_address" : "0x2900c23cc",
      "native_offset" : "0x00000"
   }
,
  {
      "is_managed" : "false",
      "native_address" : "0x18b4dea84",
      "native_offset" : "0x00000"
   }
,
  {
      "is_managed" : "false",
      "native_address" : "0x29020a810",
      "native_offset" : "0x00000"
   }
,
  {
      "is_managed" : "false",
      "native_address" : "0x2901bda54",
      "native_offset" : "0x00000"
   }
,
  {
      "is_managed" : "false",
      "native_address" : "0x2901bd46c",
      "native_offset" : "0x00000"
   }
,
  {
      "is_managed" : "false",
      "native_address" : "0x2901b9284",
      "native_offset" : "0x00000"
   }
,
  {
      "is_managed" : "false",
      "native_address" : "0x2901b9130",
      "native_offset" : "0x00000"
   }
,
  {
      "is_managed" : "false",
      "native_address" : "0x290238cf8",
      "native_offset" : "0x00000"
   }
,
  {
      "is_managed" : "false",
      "native_address" : "0x290238c80",
      "native_offset" : "0x00000"
   }
,
  {
      "is_managed" : "false",
      "native_address" : "0x18b4affa8",
      "native_offset" : "0x00000"
   }
,
  {
      "is_managed" : "false",
      "native_address" : "0x18b4aada0",
      "native_offset" : "0x00000"
   }

  ]
 },
 {
    "is_managed" : true,
    "offset_free_hash" : "0xf032b137c",
    "offset_rich_hash" : "0xf032b1502",
    "crashed" : false,
    "native_thread_id" : "0x2a6687000",
    "thread_info_addr" : "0x293e6ec00",
    "thread_name" : "ServerSocket-UnityServer-Sender",
    "ctx" : {
      "IP" : "0x18b473710",
      "SP" : "0x2a6686350",
      "BP" : "0x2a66863e0"
  },
    "managed_frames" : [
  {
      "is_managed" : "false",
      "native_address" : "unregistered"
   }
,
  {
      "is_managed" : "true",
      "guid" : "A9C3DED0-9DCB-4B3E-A021-286A5A859400",
      "token" : "0x00000",
      "native_offset" : "0x0",
      "filename" : "mscorlib.dll",
      "sizeofimage" : "0x470000",
      "timestamp" : "0xd7d06e8b",
      "il_offset" : "0xffffffff"
   }
,
  {
      "is_managed" : "true",
      "guid" : "A9C3DED0-9DCB-4B3E-A021-286A5A859400",
      "token" : "0x6001f5d",
      "native_offset" : "0x0",
      "filename" : "mscorlib.dll",
      "sizeofimage" : "0x470000",
      "timestamp" : "0xd7d06e8b",
      "il_offset" : "0x0002f"
   }
,
  {
      "is_managed" : "true",
      "guid" : "A9C3DED0-9DCB-4B3E-A021-286A5A859400",
      "token" : "0x6001f50",
      "native_offset" : "0x0",
      "filename" : "mscorlib.dll",
      "sizeofimage" : "0x470000",
      "timestamp" : "0xd7d06e8b",
      "il_offset" : "0x0000e"
   }
,
  {
      "is_managed" : "true",
      "guid" : "A9C3DED0-9DCB-4B3E-A021-286A5A859400",
      "token" : "0x6001f54",
      "native_offset" : "0x0",
      "filename" : "mscorlib.dll",
      "sizeofimage" : "0x470000",
      "timestamp" : "0xd7d06e8b",
      "il_offset" : "0x00000"
   }
,
  {
      "is_managed" : "true",
      "guid" : "2DE3E765-F8EE-43F6-9C7F-A88DCB060C8A",
      "token" : "0x600039b",
      "native_offset" : "0x0",
      "filename" : "JetBrains.Rider.Unity.Editor.Plugin.Net46.Repacked",
      "sizeofimage" : "0x9c000",
      "timestamp" : "0x0",
      "il_offset" : "0x0002d"
   }
,
  {
      "is_managed" : "true",
      "guid" : "2DE3E765-F8EE-43F6-9C7F-A88DCB060C8A",
      "token" : "0x6000398",
      "native_offset" : "0x0",
      "filename" : "JetBrains.Rider.Unity.Editor.Plugin.Net46.Repacked",
      "sizeofimage" : "0x9c000",
      "timestamp" : "0x0",
      "il_offset" : "0x00000"
   }
,
  {
      "is_managed" : "true",
      "guid" : "A9C3DED0-9DCB-4B3E-A021-286A5A859400",
      "token" : "0x6001f7d",
      "native_offset" : "0x0",
      "filename" : "mscorlib.dll",
      "sizeofimage" : "0x470000",
      "timestamp" : "0xd7d06e8b",
      "il_offset" : "0x00014"
   }
,
  {
      "is_managed" : "true",
      "guid" : "A9C3DED0-9DCB-4B3E-A021-286A5A859400",
      "token" : "0x6001f25",
      "native_offset" : "0x0",
      "filename" : "mscorlib.dll",
      "sizeofimage" : "0x470000",
      "timestamp" : "0xd7d06e8b",
      "il_offset" : "0x00071"
   }
,
  {
      "is_managed" : "true",
      "guid" : "A9C3DED0-9DCB-4B3E-A021-286A5A859400",
      "token" : "0x6001f23",
      "native_offset" : "0x0",
      "filename" : "mscorlib.dll",
      "sizeofimage" : "0x470000",
      "timestamp" : "0xd7d06e8b",
      "il_offset" : "0x00000"
   }
,
  {
      "is_managed" : "true",
      "guid" : "A9C3DED0-9DCB-4B3E-A021-286A5A859400",
      "token" : "0x6001f22",
      "native_offset" : "0x0",
      "filename" : "mscorlib.dll",
      "sizeofimage" : "0x470000",
      "timestamp" : "0xd7d06e8b",
      "il_offset" : "0x0002b"
   }
,
  {
      "is_managed" : "true",
      "guid" : "A9C3DED0-9DCB-4B3E-A021-286A5A859400",
      "token" : "0x6001f7f",
      "native_offset" : "0x0",
      "filename" : "mscorlib.dll",
      "sizeofimage" : "0x470000",
      "timestamp" : "0xd7d06e8b",
      "il_offset" : "0x00008"
   }
,
  {
      "is_managed" : "true",
      "guid" : "A9C3DED0-9DCB-4B3E-A021-286A5A859400",
      "token" : "0x00000",
      "native_offset" : "0x0",
      "filename" : "mscorlib.dll",
      "sizeofimage" : "0x470000",
      "timestamp" : "0xd7d06e8b",
      "il_offset" : "0x00065"
   }

  ],
  "unmanaged_frames" : [
 {
    "is_managed" : "false",
    "native_address" : "0x29008119c",
    "native_offset" : "0x00000"
  }
,
 {
    "is_managed" : "false",
    "native_address" : "0x2901b8518",
    "native_offset" : "0x00000"
  }
,
 {
    "is_managed" : "false",
    "native_address" : "0x2901b8874",
    "native_offset" : "0x00000"
  }
,
 {
    "is_managed" : "false",
    "native_address" : "0x2901b863c",
    "native_offset" : "0x00000"
  }
,
 {
    "is_managed" : "false",
    "native_address" : "0x2900c23cc",
    "native_offset" : "0x00000"
  }
,
 {
    "is_managed" : "false",
    "native_address" : "0x18b4dea84",
    "native_offset" : "0x00000"
  }
,
 {
    "is_managed" : "false",
    "native_address" : "0x18b4b0574",
    "native_offset" : "0x00000"
  }
,
 {
    "is_managed" : "false",
    "native_address" : "0x290207d94",
    "native_offset" : "0x00000"
  }
,
 {
    "is_managed" : "false",
    "native_address" : "0x2901c4248",
    "native_offset" : "0x00000"
  }
,
 {
    "is_managed" : "false",
    "native_address" : "0x2901c407c",
    "native_offset" : "0x00000"
  }
,
 {
    "is_managed" : "false",
    "native_address" : "0x2901f34bc",
    "native_offset" : "0x00000"
  }
,
 {
    "is_managed" : "false",
    "native_address" : "0x29015c730",
    "native_offset" : "0x00000"
  }
,
 {
    "is_managed" : "true",
    "guid" : "A9C3DED0-9DCB-4B3E-A021-286A5A859400",
    "token" : "0x00000",
    "native_offset" : "0x0",
    "filename" : "mscorlib.dll",
    "sizeofimage" : "0x470000",
    "timestamp" : "0xd7d06e8b",
    "il_offset" : "0x00000"
  }
,
 {
    "is_managed" : "true",
    "guid" : "A9C3DED0-9DCB-4B3E-A021-286A5A859400",
    "token" : "0x6001f5d",
    "native_offset" : "0x0",
    "filename" : "mscorlib.dll",
    "sizeofimage" : "0x470000",
    "timestamp" : "0xd7d06e8b",
    "il_offset" : "0x00000"
  }
,
 {
    "is_managed" : "true",
    "guid" : "A9C3DED0-9DCB-4B3E-A021-286A5A859400",
    "token" : "0x6001f50",
    "native_offset" : "0x0",
    "filename" : "mscorlib.dll",
    "sizeofimage" : "0x470000",
    "timestamp" : "0xd7d06e8b",
    "il_offset" : "0x00000"
  }
,
 {
    "is_managed" : "true",
    "guid" : "A9C3DED0-9DCB-4B3E-A021-286A5A859400",
    "token" : "0x6001f54",
    "native_offset" : "0x0",
    "filename" : "mscorlib.dll",
    "sizeofimage" : "0x470000",
    "timestamp" : "0xd7d06e8b",
    "il_offset" : "0x00000"
  }
,
 {
    "is_managed" : "true",
    "guid" : "2DE3E765-F8EE-43F6-9C7F-A88DCB060C8A",
    "token" : "0x600039b",
    "native_offset" : "0x0",
    "filename" : "JetBrains.Rider.Unity.Editor.Plugin.Net46.Repacked",
    "sizeofimage" : "0x9c000",
    "timestamp" : "0x0",
    "il_offset" : "0x00000"
  }
,
 {
    "is_managed" : "true",
    "guid" : "2DE3E765-F8EE-43F6-9C7F-A88DCB060C8A",
    "token" : "0x6000398",
    "native_offset" : "0x0",
    "filename" : "JetBrains.Rider.Unity.Editor.Plugin.Net46.Repacked",
    "sizeofimage" : "0x9c000",
    "timestamp" : "0x0",
    "il_offset" : "0x00000"
  }
,
 {
    "is_managed" : "true",
    "guid" : "A9C3DED0-9DCB-4B3E-A021-286A5A859400",
    "token" : "0x6001f7d",
    "native_offset" : "0x0",
    "filename" : "mscorlib.dll",
    "sizeofimage" : "0x470000",
    "timestamp" : "0xd7d06e8b",
    "il_offset" : "0x00000"
  }
,
 {
    "is_managed" : "true",
    "guid" : "A9C3DED0-9DCB-4B3E-A021-286A5A859400",
    "token" : "0x6001f25",
    "native_offset" : "0x0",
    "filename" : "mscorlib.dll",
    "sizeofimage" : "0x470000",
    "timestamp" : "0xd7d06e8b",
    "il_offset" : "0x00000"
  }
,
 {
    "is_managed" : "true",
    "guid" : "A9C3DED0-9DCB-4B3E-A021-286A5A859400",
    "token" : "0x6001f23",
    "native_offset" : "0x0",
    "filename" : "mscorlib.dll",
    "sizeofimage" : "0x470000",
    "timestamp" : "0xd7d06e8b",
    "il_offset" : "0x00000"
  }
,
 {
    "is_managed" : "true",
    "guid" : "A9C3DED0-9DCB-4B3E-A021-286A5A859400",
    "token" : "0x6001f22",
    "native_offset" : "0x0",
    "filename" : "mscorlib.dll",
    "sizeofimage" : "0x470000",
    "timestamp" : "0xd7d06e8b",
    "il_offset" : "0x00000"
  }
,
 {
    "is_managed" : "true",
    "guid" : "A9C3DED0-9DCB-4B3E-A021-286A5A859400",
    "token" : "0x6001f7f",
    "native_offset" : "0x0",
    "filename" : "mscorlib.dll",
    "sizeofimage" : "0x470000",
    "timestamp" : "0xd7d06e8b",
    "il_offset" : "0x00000"
  }
,
 {
    "is_managed" : "true",
    "guid" : "A9C3DED0-9DCB-4B3E-A021-286A5A859400",
    "token" : "0x00000",
    "native_offset" : "0x0",
    "filename" : "mscorlib.dll",
    "sizeofimage" : "0x470000",
    "timestamp" : "0xd7d06e8b",
    "il_offset" : "0x00000"
  }
,
 {
    "is_managed" : "false",
    "native_address" : "0x290010d84",
    "native_offset" : "0x00000"
  }
,
 {
    "is_managed" : "false",
    "native_address" : "0x29019724c",
    "native_offset" : "0x00000"
  }
,
 {
    "is_managed" : "false",
    "native_address" : "0x290198e5c",
    "native_offset" : "0x00000"
  }
,
 {
    "is_managed" : "false",
    "native_address" : "0x2901b9378",
    "native_offset" : "0x00000"
  }
,
 {
    "is_managed" : "false",
    "native_address" : "0x2901b9130",
    "native_offset" : "0x00000"
  }
,
 {
    "is_managed" : "false",
    "native_address" : "0x290238cf8",
    "native_offset" : "0x00000"
  }
,
 {
    "is_managed" : "false",
    "native_address" : "0x290238c80",
    "native_offset" : "0x00000"
  }
,
 {
    "is_managed" : "false",
    "native_address" : "0x18b4affa8",
    "native_offset" : "0x00000"
  }
,
 {
    "is_managed" : "false",
    "native_address" : "0x18b4aada0",
    "native_offset" : "0x00000"
  }

 ]
},
{
  "is_managed" : false,
  "offset_free_hash" : "0x0",
  "offset_rich_hash" : "0x0",
  "crashed" : false,
  "native_thread_id" : "0x2908ab000",
  "thread_info_addr" : "0x1350f5800",
  "thread_name" : "Finalizer",
  "ctx" : {
    "IP" : "0x18b46fe90",
    "SP" : "0x2908aadd0",
    "BP" : "0x2908aae50"
 },
  "unmanaged_frames" : [
 {
    "is_managed" : "false",
    "native_address" : "0x29008119c",
    "native_offset" : "0x00000"
  }
,
 {
    "is_managed" : "false",
    "native_address" : "0x2901b8518",
    "native_offset" : "0x00000"
  }
,
 {
    "is_managed" : "false",
    "native_address" : "0x2901b8874",
    "native_offset" : "0x00000"
  }
,
 {
    "is_managed" : "false",
    "native_address" : "0x2901b863c",
    "native_offset" : "0x00000"
  }
,
 {
    "is_managed" : "false",
    "native_address" : "0x2900c23cc",
    "native_offset" : "0x00000"
  }
,
 {
    "is_managed" : "false",
    "native_address" : "0x18b4dea84",
    "native_offset" : "0x00000"
  }
,
 {
    "is_managed" : "false",
    "native_address" : "0x2901f216c",
    "native_offset" : "0x00000"
  }
,
 {
    "is_managed" : "false",
    "native_address" : "0x2901b9284",
    "native_offset" : "0x00000"
  }
,
 {
    "is_managed" : "false",
    "native_address" : "0x2901b9130",
    "native_offset" : "0x00000"
  }
,
 {
    "is_managed" : "false",
    "native_address" : "0x290238cf8",
    "native_offset" : "0x00000"
  }
,
 {
    "is_managed" : "false",
    "native_address" : "0x290238c80",
    "native_offset" : "0x00000"
  }
,
 {
    "is_managed" : "false",
    "native_address" : "0x18b4affa8",
    "native_offset" : "0x00000"
  }
,
 {
    "is_managed" : "false",
    "native_address" : "0x18b4aada0",
    "native_offset" : "0x00000"
  }

 ]
},
{
  "is_managed" : false,
  "offset_free_hash" : "0x0",
  "offset_rich_hash" : "0x0",
  "crashed" : true,
  "native_thread_id" : "0x1e691db40",
  "thread_info_addr" : "0x135080000",
  "thread_name" : "tid_103",
  "ctx" : {
    "IP" : "0x10377fa30",
    "SP" : "0x16f1de460",
    "BP" : "0x16f1de4d0"
 },
  "unmanaged_frames" : [
 {
    "is_managed" : "false",
    "native_address" : "0x29008119c",
    "native_offset" : "0x00000"
  }
,
 {
    "is_managed" : "false",
    "native_address" : "0x2901b8518",
    "native_offset" : "0x00000"
  }
,
 {
    "is_managed" : "false",
    "native_address" : "0x2901b8874",
    "native_offset" : "0x00000"
  }
,
 {
    "is_managed" : "false",
    "native_address" : "0x2901b8e64",
    "native_offset" : "0x00000"
  }
,
 {
    "is_managed" : "false",
    "native_address" : "0x2900c3218",
    "native_offset" : "0x00000"
  }
,
 {
    "is_managed" : "false",
    "native_address" : "0x290085334",
    "native_offset" : "0x00000"
  }
,
 {
    "is_managed" : "false",
    "native_address" : "0x29000dac4",
    "native_offset" : "0x00000"
  }
,
 {
    "is_managed" : "false",
    "native_address" : "0x18b4dea84",
    "native_offset" : "0x00000"
  }
,
 {
    "is_managed" : "false",
    "native_address" : "0x10377fa30",
    "native_offset" : "0x00000"
  }
,
 {
    "is_managed" : "false",
    "native_address" : "0x10379c5b8",
    "native_offset" : "0x00000"
  }
,
 {
    "is_managed" : "false",
    "native_address" : "0x1023919b8",
    "native_offset" : "0x00000"
  }
,
 {
    "is_managed" : "false",
    "native_address" : "0x1037aa118",
    "native_offset" : "0x00000"
  }
,
 {
    "is_managed" : "false",
    "native_address" : "0x1037aa310",
    "native_offset" : "0x00000"
  }
,
 {
    "is_managed" : "false",
    "native_address" : "0x18e94e474",
    "native_offset" : "0x00000"
  }
,
 {
    "is_managed" : "false",
    "native_address" : "0x18e8d90dc",
    "native_offset" : "0x00000"
  }
,
 {
    "is_managed" : "false",
    "native_address" : "0x18e8d8d9c",
    "native_offset" : "0x00000"
  }
,
 {
    "is_managed" : "false",
    "native_address" : "0x18e8d80e0",
    "native_offset" : "0x00000"
  }
,
 {
    "is_managed" : "false",
    "native_address" : "0x1037a10cc",
    "native_offset" : "0x00000"
  }
,
 {
    "is_managed" : "false",
    "native_address" : "0x18eb280f0",
    "native_offset" : "0x00000"
  }
,
 {
    "is_managed" : "false",
    "native_address" : "0x18e79f57c",
    "native_offset" : "0x00000"
  }
,
 {
    "is_managed" : "false",
    "native_address" : "0x18e7769a8",
    "native_offset" : "0x00000"
  }
,
 {
    "is_managed" : "false",
    "native_address" : "0x1037a19a0",
    "native_offset" : "0x00000"
  }
,
 {
    "is_managed" : "false",
    "native_address" : "0x1037a1d04",
    "native_offset" : "0x00000"
  }
,
 {
    "is_managed" : "false",
    "native_address" : "0x18b157f28",
    "native_offset" : "0x00000"
  }

 ]
},
{
  "is_managed" : false,
  "offset_free_hash" : "0x0",
  "offset_rich_hash" : "0x0",
  "crashed" : false,
  "native_thread_id" : "0x2b8b0f000",
  "thread_info_addr" : "0x13000b000",
  "thread_name" : "Thread Pool Worker",
  "ctx" : {
    "IP" : "0x18b46fea8",
    "SP" : "0x2b8b0edb0",
    "BP" : "0x2b8b0ee50"
 },
  "unmanaged_frames" : [
 {
    "is_managed" : "false",
    "native_address" : "0x29008119c",
    "native_offset" : "0x00000"
  }
,
 {
    "is_managed" : "false",
    "native_address" : "0x2901b8518",
    "native_offset" : "0x00000"
  }
,
 {
    "is_managed" : "false",
    "native_address" : "0x2901b8874",
    "native_offset" : "0x00000"
  }
,
 {
    "is_managed" : "false",
    "native_address" : "0x2901b863c",
    "native_offset" : "0x00000"
  }
,
 {
    "is_managed" : "false",
    "native_address" : "0x2900c23cc",
    "native_offset" : "0x00000"
  }
,
 {
    "is_managed" : "false",
    "native_address" : "0x18b4dea84",
    "native_offset" : "0x00000"
  }
,
 {
    "is_managed" : "false",
    "native_address" : "0x2901111c0",
    "native_offset" : "0x00000"
  }
,
 {
    "is_managed" : "false",
    "native_address" : "0x2901b9284",
    "native_offset" : "0x00000"
  }
,
 {
    "is_managed" : "false",
    "native_address" : "0x2901b9130",
    "native_offset" : "0x00000"
  }
,
 {
    "is_managed" : "false",
    "native_address" : "0x290238cf8",
    "native_offset" : "0x00000"
  }
,
 {
    "is_managed" : "false",
    "native_address" : "0x290238c80",
    "native_offset" : "0x00000"
  }
,
 {
    "is_managed" : "false",
    "native_address" : "0x18b4affa8",
    "native_offset" : "0x00000"
  }
,
 {
    "is_managed" : "false",
    "native_address" : "0x18b4aada0",
    "native_offset" : "0x00000"
  }

 ]
},
{
  "is_managed" : false,
  "offset_free_hash" : "0x0",
  "offset_rich_hash" : "0x0",
  "crashed" : false,
  "native_thread_id" : "0x2b8ffb000",
  "thread_info_addr" : "0x130029200",
  "thread_name" : "Thread Pool Worker",
  "ctx" : {
    "IP" : "0x18b46fea8",
    "SP" : "0x2b8ffadb0",
    "BP" : "0x2b8ffae50"
 },
  "unmanaged_frames" : [
 {
    "is_managed" : "false",
    "native_address" : "0x29008119c",
    "native_offset" : "0x00000"
  }
,
 {
    "is_managed" : "false",
    "native_address" : "0x2901b8518",
    "native_offset" : "0x00000"
  }
,
 {
    "is_managed" : "false",
    "native_address" : "0x2901b8874",
    "native_offset" : "0x00000"
  }
,
 {
    "is_managed" : "false",
    "native_address" : "0x2901b863c",
    "native_offset" : "0x00000"
  }
,
 {
    "is_managed" : "false",
    "native_address" : "0x2900c23cc",
    "native_offset" : "0x00000"
  }
,
 {
    "is_managed" : "false",
    "native_address" : "0x18b4dea84",
    "native_offset" : "0x00000"
  }
,
 {
    "is_managed" : "false",
    "native_address" : "0x2901111c0",
    "native_offset" : "0x00000"
  }
,
 {
    "is_managed" : "false",
    "native_address" : "0x2901b9284",
    "native_offset" : "0x00000"
  }
,
 {
    "is_managed" : "false",
    "native_address" : "0x2901b9130",
    "native_offset" : "0x00000"
  }
,
 {
    "is_managed" : "false",
    "native_address" : "0x290238cf8",
    "native_offset" : "0x00000"
  }
,
 {
    "is_managed" : "false",
    "native_address" : "0x290238c80",
    "native_offset" : "0x00000"
  }
,
 {
    "is_managed" : "false",
    "native_address" : "0x18b4affa8",
    "native_offset" : "0x00000"
  }
,
 {
    "is_managed" : "false",
    "native_address" : "0x18b4aada0",
    "native_offset" : "0x00000"
  }

 ]
},
{
  "is_managed" : true,
  "offset_free_hash" : "0xd8fc9c192",
  "offset_rich_hash" : "0xd8fc9c2f3",
  "crashed" : false,
  "native_thread_id" : "0x2a6893000",
  "thread_info_addr" : "0x31c8eaa00",
  "thread_name" : "ServerSocket-UnityServer-Receiver",
  "ctx" : {
    "IP" : "0x18b478808",
    "SP" : "0x2a68925f0",
    "BP" : "0x2a6892660"
 },
  "managed_frames" : [
 {
    "is_managed" : "false",
    "native_address" : "unregistered"
  }
,
 {
    "is_managed" : "true",
    "guid" : "181E47A7-B791-40EA-BD9F-CD79FECAE66A",
    "token" : "0x00000",
    "native_offset" : "0x0",
    "filename" : "System.dll",
    "sizeofimage" : "0x29a000",
    "timestamp" : "0x814d5962",
    "il_offset" : "0xffffffff"
  }
,
 {
    "is_managed" : "true",
    "guid" : "181E47A7-B791-40EA-BD9F-CD79FECAE66A",
    "token" : "0x6003f7c",
    "native_offset" : "0x0",
    "filename" : "System.dll",
    "sizeofimage" : "0x29a000",
    "timestamp" : "0x814d5962",
    "il_offset" : "0x0000c"
  }
,
 {
    "is_managed" : "true",
    "guid" : "181E47A7-B791-40EA-BD9F-CD79FECAE66A",
    "token" : "0x6003f75",
    "native_offset" : "0x0",
    "filename" : "System.dll",
    "sizeofimage" : "0x29a000",
    "timestamp" : "0x814d5962",
    "il_offset" : "0x00008"
  }
,
 {
    "is_managed" : "true",
    "guid" : "2DE3E765-F8EE-43F6-9C7F-A88DCB060C8A",
    "token" : "0x6000fc0",
    "native_offset" : "0x0",
    "filename" : "JetBrains.Rider.Unity.Editor.Plugin.Net46.Repacked",
    "sizeofimage" : "0x9c000",
    "timestamp" : "0x0",
    "il_offset" : "0x00031"
  }
,
 {
    "is_managed" : "true",
    "guid" : "2DE3E765-F8EE-43F6-9C7F-A88DCB060C8A",
    "token" : "0x600065d",
    "native_offset" : "0x0",
    "filename" : "JetBrains.Rider.Unity.Editor.Plugin.Net46.Repacked",
    "sizeofimage" : "0x9c000",
    "timestamp" : "0x0",
    "il_offset" : "0x00000"
  }
,
 {
    "is_managed" : "true",
    "guid" : "2DE3E765-F8EE-43F6-9C7F-A88DCB060C8A",
    "token" : "0x6000fbf",
    "native_offset" : "0x0",
    "filename" : "JetBrains.Rider.Unity.Editor.Plugin.Net46.Repacked",
    "sizeofimage" : "0x9c000",
    "timestamp" : "0x0",
    "il_offset" : "0x00000"
  }
,
 {
    "is_managed" : "true",
    "guid" : "A9C3DED0-9DCB-4B3E-A021-286A5A859400",
    "token" : "0x6001f7d",
    "native_offset" : "0x0",
    "filename" : "mscorlib.dll",
    "sizeofimage" : "0x470000",
    "timestamp" : "0xd7d06e8b",
    "il_offset" : "0x00014"
  }
,
 {
    "is_managed" : "true",
    "guid" : "A9C3DED0-9DCB-4B3E-A021-286A5A859400",
    "token" : "0x6001f25",
    "native_offset" : "0x0",
    "filename" : "mscorlib.dll",
    "sizeofimage" : "0x470000",
    "timestamp" : "0xd7d06e8b",
    "il_offset" : "0x00071"
  }
,
 {
    "is_managed" : "true",
    "guid" : "A9C3DED0-9DCB-4B3E-A021-286A5A859400",
    "token" : "0x6001f23",
    "native_offset" : "0x0",
    "filename" : "mscorlib.dll",
    "sizeofimage" : "0x470000",
    "timestamp" : "0xd7d06e8b",
    "il_offset" : "0x00000"
  }
,
 {
    "is_managed" : "true",
    "guid" : "A9C3DED0-9DCB-4B3E-A021-286A5A859400",
    "token" : "0x6001f22",
    "native_offset" : "0x0",
    "filename" : "mscorlib.dll",
    "sizeofimage" : "0x470000",
    "timestamp" : "0xd7d06e8b",
    "il_offset" : "0x0002b"
  }
,
 {
    "is_managed" : "true",
    "guid" : "A9C3DED0-9DCB-4B3E-A021-286A5A859400",
    "token" : "0x6001f7f",
    "native_offset" : "0x0",
    "filename" : "mscorlib.dll",
    "sizeofimage" : "0x470000",
    "timestamp" : "0xd7d06e8b",
    "il_offset" : "0x00008"
  }
,
 {
    "is_managed" : "true",
    "guid" : "A9C3DED0-9DCB-4B3E-A021-286A5A859400",
    "token" : "0x00000",
    "native_offset" : "0x0",
    "filename" : "mscorlib.dll",
    "sizeofimage" : "0x470000",
    "timestamp" : "0xd7d06e8b",
    "il_offset" : "0x00065"
  }

 ],
"unmanaged_frames" : [
{
  "is_managed" : "false",
  "native_address" : "0x29008119c",
  "native_offset" : "0x00000"
 }
,
{
  "is_managed" : "false",
  "native_address" : "0x2901b8518",
  "native_offset" : "0x00000"
 }
,
{
  "is_managed" : "false",
  "native_address" : "0x2901b8874",
  "native_offset" : "0x00000"
 }
,
{
  "is_managed" : "false",
  "native_address" : "0x2901b863c",
  "native_offset" : "0x00000"
 }
,
{
  "is_managed" : "false",
  "native_address" : "0x2900c23cc",
  "native_offset" : "0x00000"
 }
,
{
  "is_managed" : "false",
  "native_address" : "0x18b4dea84",
  "native_offset" : "0x00000"
 }
,
{
  "is_managed" : "false",
  "native_address" : "0x290106100",
  "native_offset" : "0x00000"
 }
,
{
  "is_managed" : "false",
  "native_address" : "0x2901a10a4",
  "native_offset" : "0x00000"
 }
,
{
  "is_managed" : "true",
  "guid" : "181E47A7-B791-40EA-BD9F-CD79FECAE66A",
  "token" : "0x00000",
  "native_offset" : "0x0",
  "filename" : "System.dll",
  "sizeofimage" : "0x29a000",
  "timestamp" : "0x814d5962",
  "il_offset" : "0x00000"
 }
,
{
  "is_managed" : "true",
  "guid" : "181E47A7-B791-40EA-BD9F-CD79FECAE66A",
  "token" : "0x6003f7c",
  "native_offset" : "0x0",
  "filename" : "System.dll",
  "sizeofimage" : "0x29a000",
  "timestamp" : "0x814d5962",
  "il_offset" : "0x00000"
 }
,
{
  "is_managed" : "true",
  "guid" : "181E47A7-B791-40EA-BD9F-CD79FECAE66A",
  "token" : "0x6003f75",
  "native_offset" : "0x0",
  "filename" : "System.dll",
  "sizeofimage" : "0x29a000",
  "timestamp" : "0x814d5962",
  "il_offset" : "0x00000"
 }
,
{
  "is_managed" : "true",
  "guid" : "2DE3E765-F8EE-43F6-9C7F-A88DCB060C8A",
  "token" : "0x6000fc0",
  "native_offset" : "0x0",
  "filename" : "JetBrains.Rider.Unity.Editor.Plugin.Net46.Repacked",
  "sizeofimage" : "0x9c000",
  "timestamp" : "0x0",
  "il_offset" : "0x00000"
 }
,
{
  "is_managed" : "true",
  "guid" : "2DE3E765-F8EE-43F6-9C7F-A88DCB060C8A",
  "token" : "0x600065d",
  "native_offset" : "0x0",
  "filename" : "JetBrains.Rider.Unity.Editor.Plugin.Net46.Repacked",
  "sizeofimage" : "0x9c000",
  "timestamp" : "0x0",
  "il_offset" : "0x00000"
 }
,
{
  "is_managed" : "true",
  "guid" : "2DE3E765-F8EE-43F6-9C7F-A88DCB060C8A",
  "token" : "0x6000fbf",
  "native_offset" : "0x0",
  "filename" : "JetBrains.Rider.Unity.Editor.Plugin.Net46.Repacked",
  "sizeofimage" : "0x9c000",
  "timestamp" : "0x0",
  "il_offset" : "0x00000"
 }
,
{
  "is_managed" : "true",
  "guid" : "A9C3DED0-9DCB-4B3E-A021-286A5A859400",
  "token" : "0x6001f7d",
  "native_offset" : "0x0",
  "filename" : "mscorlib.dll",
  "sizeofimage" : "0x470000",
  "timestamp" : "0xd7d06e8b",
  "il_offset" : "0x00000"
 }
,
{
  "is_managed" : "true",
  "guid" : "A9C3DED0-9DCB-4B3E-A021-286A5A859400",
  "token" : "0x6001f25",
  "native_offset" : "0x0",
  "filename" : "mscorlib.dll",
  "sizeofimage" : "0x470000",
  "timestamp" : "0xd7d06e8b",
  "il_offset" : "0x00000"
 }
,
{
  "is_managed" : "true",
  "guid" : "A9C3DED0-9DCB-4B3E-A021-286A5A859400",
  "token" : "0x6001f23",
  "native_offset" : "0x0",
  "filename" : "mscorlib.dll",
  "sizeofimage" : "0x470000",
  "timestamp" : "0xd7d06e8b",
  "il_offset" : "0x00000"
 }
,
{
  "is_managed" : "true",
  "guid" : "A9C3DED0-9DCB-4B3E-A021-286A5A859400",
  "token" : "0x6001f22",
  "native_offset" : "0x0",
  "filename" : "mscorlib.dll",
  "sizeofimage" : "0x470000",
  "timestamp" : "0xd7d06e8b",
  "il_offset" : "0x00000"
 }
,
{
  "is_managed" : "true",
  "guid" : "A9C3DED0-9DCB-4B3E-A021-286A5A859400",
  "token" : "0x6001f7f",
  "native_offset" : "0x0",
  "filename" : "mscorlib.dll",
  "sizeofimage" : "0x470000",
  "timestamp" : "0xd7d06e8b",
  "il_offset" : "0x00000"
 }
,
{
  "is_managed" : "true",
  "guid" : "A9C3DED0-9DCB-4B3E-A021-286A5A859400",
  "token" : "0x00000",
  "native_offset" : "0x0",
  "filename" : "mscorlib.dll",
  "sizeofimage" : "0x470000",
  "timestamp" : "0xd7d06e8b",
  "il_offset" : "0x00000"
 }
,
{
  "is_managed" : "false",
  "native_address" : "0x290010d84",
  "native_offset" : "0x00000"
 }
,
{
  "is_managed" : "false",
  "native_address" : "0x29019724c",
  "native_offset" : "0x00000"
 }
,
{
  "is_managed" : "false",
  "native_address" : "0x290198e5c",
  "native_offset" : "0x00000"
 }
,
{
  "is_managed" : "false",
  "native_address" : "0x2901b9378",
  "native_offset" : "0x00000"
 }
,
{
  "is_managed" : "false",
  "native_address" : "0x2901b9130",
  "native_offset" : "0x00000"
 }
,
{
  "is_managed" : "false",
  "native_address" : "0x290238cf8",
  "native_offset" : "0x00000"
 }
,
{
  "is_managed" : "false",
  "native_address" : "0x290238c80",
  "native_offset" : "0x00000"
 }
,
{
  "is_managed" : "false",
  "native_address" : "0x18b4affa8",
  "native_offset" : "0x00000"
 }
,
{
  "is_managed" : "false",
  "native_address" : "0x18b4aada0",
  "native_offset" : "0x00000"
 }

]
},
{
"is_managed" : false,
"offset_free_hash" : "0x0",
"offset_rich_hash" : "0x0",
"crashed" : false,
"native_thread_id" : "0x2b865f000",
"thread_info_addr" : "0x131834600",
"thread_name" : "tid_3cd47",
"ctx" : {
  "IP" : "0x18b473710",
  "SP" : "0x2b865ec20",
  "BP" : "0x2b865ecb0"
},
"unmanaged_frames" : [
{
  "is_managed" : "false",
  "native_address" : "0x29008119c",
  "native_offset" : "0x00000"
 }
,
{
  "is_managed" : "false",
  "native_address" : "0x2901b8518",
  "native_offset" : "0x00000"
 }
,
{
  "is_managed" : "false",
  "native_address" : "0x2901b8874",
  "native_offset" : "0x00000"
 }
,
{
  "is_managed" : "false",
  "native_address" : "0x2901b863c",
  "native_offset" : "0x00000"
 }
,
{
  "is_managed" : "false",
  "native_address" : "0x2900c23cc",
  "native_offset" : "0x00000"
 }
,
{
  "is_managed" : "false",
  "native_address" : "0x18b4dea84",
  "native_offset" : "0x00000"
 }
,
{
  "is_managed" : "false",
  "native_address" : "0x18b4b05a0",
  "native_offset" : "0x00000"
 }
,
{
  "is_managed" : "false",
  "native_address" : "0x290207d6c",
  "native_offset" : "0x00000"
 }
,
{
  "is_managed" : "false",
  "native_address" : "0x290211a48",
  "native_offset" : "0x00000"
 }
,
{
  "is_managed" : "false",
  "native_address" : "0x2901109c8",
  "native_offset" : "0x00000"
 }
,
{
  "is_managed" : "false",
  "native_address" : "0x2901b9284",
  "native_offset" : "0x00000"
 }
,
{
  "is_managed" : "false",
  "native_address" : "0x2901b9130",
  "native_offset" : "0x00000"
 }
,
{
  "is_managed" : "false",
  "native_address" : "0x290238cf8",
  "native_offset" : "0x00000"
 }
,
{
  "is_managed" : "false",
  "native_address" : "0x290238c80",
  "native_offset" : "0x00000"
 }
,
{
  "is_managed" : "false",
  "native_address" : "0x18b4affa8",
  "native_offset" : "0x00000"
 }
,
{
  "is_managed" : "false",
  "native_address" : "0x18b4aada0",
  "native_offset" : "0x00000"
 }

]
},
{
"is_managed" : false,
"offset_free_hash" : "0x0",
"offset_rich_hash" : "0x0",
"crashed" : false,
"native_thread_id" : "0x177d5f000",
"thread_info_addr" : "0x294243200",
"thread_name" : "tid_1020f",
"ctx" : {
  "IP" : "0x18b46fe90",
  "SP" : "0x177d5ece0",
  "BP" : "0x177d5ecf0"
},
"unmanaged_frames" : [
{
  "is_managed" : "false",
  "native_address" : "0x29008119c",
  "native_offset" : "0x00000"
 }
,
{
  "is_managed" : "false",
  "native_address" : "0x2901b8518",
  "native_offset" : "0x00000"
 }
,
{
  "is_managed" : "false",
  "native_address" : "0x2901b8874",
  "native_offset" : "0x00000"
 }
,
{
  "is_managed" : "false",
  "native_address" : "0x2901b863c",
  "native_offset" : "0x00000"
 }
,
{
  "is_managed" : "false",
  "native_address" : "0x2900c23cc",
  "native_offset" : "0x00000"
 }
,
{
  "is_managed" : "false",
  "native_address" : "0x18b4dea84",
  "native_offset" : "0x00000"
 }
,
{
  "is_managed" : "false",
  "native_address" : "0x18b30099c",
  "native_offset" : "0x00000"
 }
,
{
  "is_managed" : "false",
  "native_address" : "0x18b301050",
  "native_offset" : "0x00000"
 }
,
{
  "is_managed" : "false",
  "native_address" : "0x10384c6a8",
  "native_offset" : "0x00000"
 }
,
{
  "is_managed" : "false",
  "native_address" : "0x101519118",
  "native_offset" : "0x00000"
 }
,
{
  "is_managed" : "false",
  "native_address" : "0x10151a164",
  "native_offset" : "0x00000"
 }
,
{
  "is_managed" : "false",
  "native_address" : "0x1017820d4",
  "native_offset" : "0x00000"
 }
,
{
  "is_managed" : "false",
  "native_address" : "0x18b4affa8",
  "native_offset" : "0x00000"
 }
,
{
  "is_managed" : "false",
  "native_address" : "0x18b4aada0",
  "native_offset" : "0x00000"
 }

]
},
{
"is_managed" : false,
"offset_free_hash" : "0x0",
"offset_rich_hash" : "0x0",
"crashed" : false,
"native_thread_id" : "0x290ab7000",
"thread_info_addr" : "0x13511da00",
"thread_name" : "Debugger agent",
"ctx" : {
  "IP" : "0x18b478808",
  "SP" : "0x290ab6aa0",
  "BP" : "0x290ab6ae0"
},
"unmanaged_frames" : [
{
  "is_managed" : "false",
  "native_address" : "0x29008119c",
  "native_offset" : "0x00000"
 }
,
{
  "is_managed" : "false",
  "native_address" : "0x2901b8518",
  "native_offset" : "0x00000"
 }
,
{
  "is_managed" : "false",
  "native_address" : "0x2901b8874",
  "native_offset" : "0x00000"
 }
,
{
  "is_managed" : "false",
  "native_address" : "0x2901b863c",
  "native_offset" : "0x00000"
 }
,
{
  "is_managed" : "false",
  "native_address" : "0x2900c23cc",
  "native_offset" : "0x00000"
 }
,
{
  "is_managed" : "false",
  "native_address" : "0x18b4dea84",
  "native_offset" : "0x00000"
 }
,
{
  "is_managed" : "false",
  "native_address" : "0x2900f1598",
  "native_offset" : "0x00000"
 }
,
{
  "is_managed" : "false",
  "native_address" : "0x2900e8194",
  "native_offset" : "0x00000"
 }
,
{
  "is_managed" : "false",
  "native_address" : "0x2901b9284",
  "native_offset" : "0x00000"
 }
,
{
  "is_managed" : "false",
  "native_address" : "0x2901b9130",
  "native_offset" : "0x00000"
 }
,
{
  "is_managed" : "false",
  "native_address" : "0x290238cf8",
  "native_offset" : "0x00000"
 }
,
{
  "is_managed" : "false",
  "native_address" : "0x290238c80",
  "native_offset" : "0x00000"
 }
,
{
  "is_managed" : "false",
  "native_address" : "0x18b4affa8",
  "native_offset" : "0x00000"
 }
,
{
  "is_managed" : "false",
  "native_address" : "0x18b4aada0",
  "native_offset" : "0x00000"
 }

]
}
]
}